demo_orifice_calc.py
demo_orifice_calc-1.0.1.dist-info/LICENSE
demo_orifice_calc-1.0.1.dist-info/METADATA
demo_orifice_calc-1.0.1.dist-info/WHEEL
demo_orifice_calc-1.0.1.dist-info/top_level.txt
demo_orifice_calc-1.0.1.dist-info/RECORD
