Metadata-Version: 2.1
Name: demo-orifice-calc
Version: 1.0.1
Summary: Demonstration of an orifice calculation module
Home-page: UNKNOWN
Author: Darren Hewett
Author-email: 
License: MIT
Platform: UNKNOWN
Classifier: License :: OSI Approved :: MIT License
Classifier: Programming Language :: Python :: 3
Classifier: Programming Language :: Python :: 3.7
